bedrock_agentcore_starter_toolkit/__init__.py
bedrock_agentcore_starter_toolkit/cli/__init__.py
bedrock_agentcore_starter_toolkit/cli/cli.py
bedrock_agentcore_starter_toolkit/cli/cli_ui.py
bedrock_agentcore_starter_toolkit/cli/common.py
bedrock_agentcore_starter_toolkit/cli/create/__init__.py
bedrock_agentcore_starter_toolkit/cli/create/commands.py
bedrock_agentcore_starter_toolkit/cli/create/prompt_util.py
bedrock_agentcore_starter_toolkit/cli/create/import_agent/README.md
bedrock_agentcore_starter_toolkit/cli/create/import_agent/__init__.py
bedrock_agentcore_starter_toolkit/cli/create/import_agent/agent_info.py
bedrock_agentcore_starter_toolkit/cli/create/import_agent/commands.py
bedrock_agentcore_starter_toolkit/cli/evaluation/__init__.py
bedrock_agentcore_starter_toolkit/cli/evaluation/commands.py
bedrock_agentcore_starter_toolkit/cli/gateway/__init__.py
bedrock_agentcore_starter_toolkit/cli/gateway/commands.py
bedrock_agentcore_starter_toolkit/cli/identity/__init__.py
bedrock_agentcore_starter_toolkit/cli/identity/commands.py
bedrock_agentcore_starter_toolkit/cli/memory/__init__.py
bedrock_agentcore_starter_toolkit/cli/memory/commands.py
bedrock_agentcore_starter_toolkit/cli/observability/__init__.py
bedrock_agentcore_starter_toolkit/cli/observability/commands.py
bedrock_agentcore_starter_toolkit/cli/policy/__init__.py
bedrock_agentcore_starter_toolkit/cli/policy/commands.py
bedrock_agentcore_starter_toolkit/cli/runtime/__init__.py
bedrock_agentcore_starter_toolkit/cli/runtime/_configure_impl.py
bedrock_agentcore_starter_toolkit/cli/runtime/commands.py
bedrock_agentcore_starter_toolkit/cli/runtime/configuration_manager.py
bedrock_agentcore_starter_toolkit/cli/runtime/dev_command.py
bedrock_agentcore_starter_toolkit/create/__init__.py
bedrock_agentcore_starter_toolkit/create/baseline_feature.py
bedrock_agentcore_starter_toolkit/create/constants.py
bedrock_agentcore_starter_toolkit/create/generate.py
bedrock_agentcore_starter_toolkit/create/types.py
bedrock_agentcore_starter_toolkit-0.2.8.dist-info/METADATA
bedrock_agentcore_starter_toolkit-0.2.8.dist-info/WHEEL
bedrock_agentcore_starter_toolkit-0.2.8.dist-info/entry_points.txt
bedrock_agentcore_starter_toolkit-0.2.8.dist-info/licenses/LICENSE.txt
bedrock_agentcore_starter_toolkit-0.2.8.dist-info/licenses/NOTICE.txt
bedrock_agentcore_starter_toolkit-0.2.8.dist-info/RECORD
