Metadata-Version: 2.4
Name: bedrock-agentcore-starter-toolkit
Version: 0.2.8
Summary: A starter toolkit for using Bedrock AgentCore
Project-URL: Homepage, https://github.com/aws/bedrock-agentcore-starter-toolkit
Project-URL: Bug Tracker, https://github.com/aws/bedrock-agentcore-starter-toolkit/issues
Project-URL: Documentation, https://github.com/aws/bedrock-agentcore-starter-toolkit
Author-email: AWS <opensource@amazon.com>
License: Apache-2.0
License-File: LICENSE.txt
License-File: NOTICE.txt
Classifier: Development Status :: 3 - Alpha
Classifier: Intended Audience :: Developers
Classifier: License :: OSI Approved :: Apache Software License
Classifier: Operating System :: OS Independent
Classifier: Programming Language :: Python :: 3
Classifier: Programming Language :: Python :: 3.10
Classifier: Programming Language :: Python :: 3.11
Classifier: Programming Language :: Python :: 3.12
Classifier: Programming Language :: Python :: 3.13
Classifier: Topic :: Scientific/Engineering :: Artificial Intelligence
Classifier: Topic :: Software Development :: Libraries :: Python Modules
Requires-Python: >=3.10
Requires-Dist: autopep8>=2.3.2
Requires-Dist: bedrock-agentcore>=1.1.0
Requires-Dist: boto3>=1.42.1
Requires-Dist: botocore>=1.42.1
Requires-Dist: docstring-parser<1.0,>=0.15
Requires-Dist: httpx>=0.28.1
Requires-Dist: jinja2>=3.1.6
Requires-Dist: openapi-spec-validator>=0.7.2
Requires-Dist: prance>=25.4.8.0
Requires-Dist: prompt-toolkit>=3.0.51
Requires-Dist: py-openapi-schema-to-json-schema>=0.0.3
Requires-Dist: pydantic<2.41.3,>=2.0.0
Requires-Dist: pyyaml>=6.0.2
Requires-Dist: questionary>=2.1.0
Requires-Dist: requests>=2.25.0
Requires-Dist: rich>=13.0.0
Requires-Dist: ruamel-yaml>=0.18.14
Requires-Dist: starlette>=0.46.2
Requires-Dist: toml>=0.10.2
Requires-Dist: typer>=0.16.0
Requires-Dist: typing-extensions<5.0.0,>=4.13.2
Requires-Dist: urllib3>=1.26.0
Requires-Dist: uvicorn>=0.34.2
